petabunit/__init__.py
petabunit/console.py
petabunit/example.py
petabunit/log.py
petabunit/py.typed
petabunit-0.0.2.dist-info/LICENSE
petabunit-0.0.2.dist-info/METADATA
petabunit-0.0.2.dist-info/WHEEL
petabunit-0.0.2.dist-info/top_level.txt
petabunit-0.0.2.dist-info/zip-safe
petabunit-0.0.2.dist-info/RECORD
