Metadata-Version: 2.1
Name: petabunit
Version: 0.0.2
Summary: petabunit are python utilities for working with units with PEtab.
Home-page: https://github.com/matthiaskoenig/petabunit
Download-URL: https://pypi.org/project/petabunit
Author: Matthias König
Author-email: konigmatt@googlemail.com
Maintainer: Matthias Koenig
Maintainer-email: konigmatt@googlemail.com
License: LGPL-3.0
Project-URL: Source Code, https://github.com/matthiaskoenig/petabunit
Project-URL: Documentation, https://github.com/matthiaskoenig/petabunit
Project-URL: Bug Tracker, https://github.com/matthiaskoenig/petabunit/issues
Keywords: units,parameter optimization,annotation
Classifier: Development Status :: 4 - Beta
Classifier: Intended Audience :: Science/Research
Classifier: License :: OSI Approved :: GNU Lesser General Public License v3 (LGPLv3)
Classifier: Operating System :: OS Independent
Classifier: Programming Language :: Python :: 3.10
Classifier: Programming Language :: Python :: 3.11
Classifier: Programming Language :: Python :: 3.12
Classifier: Programming Language :: Python :: Implementation :: CPython
Classifier: Topic :: Scientific/Engineering
Classifier: Topic :: Scientific/Engineering :: Bio-Informatics
Requires-Python: >=3.10
License-File: LICENSE
Requires-Dist: rich >=13.7
Requires-Dist: pydantic >=2.7
Requires-Dist: petab >=0.2.9
Provides-Extra: development
Requires-Dist: pip-tools >=7.4.1 ; extra == 'development'
Requires-Dist: black >=24.3.0 ; extra == 'development'
Requires-Dist: bump2version >=1.0.1 ; extra == 'development'
Requires-Dist: isort >=5.13.2 ; extra == 'development'
Requires-Dist: tox >=4.12.2 ; extra == 'development'
Requires-Dist: flake8 >=7.0.0 ; extra == 'development'
Requires-Dist: flake8-mypy >=17.8.0 ; extra == 'development'
Requires-Dist: mypy >=1.9.0 ; extra == 'development'
Requires-Dist: pytest >=8.1.1 ; extra == 'development'
Requires-Dist: pytest-cov >=5.0.0 ; extra == 'development'
